sendpushover.py
sendpushover-1.0.2.dist-info/DESCRIPTION.rst
sendpushover-1.0.2.dist-info/METADATA
sendpushover-1.0.2.dist-info/RECORD
sendpushover-1.0.2.dist-info/WHEEL
sendpushover-1.0.2.dist-info/metadata.json
sendpushover-1.0.2.dist-info/top_level.txt
